pytest_elbase/__init__.py
pytest_elbase-0.0.2rc0.dist-info/licenses/LICENSE
pytest_elbase-0.0.2rc0.dist-info/METADATA
pytest_elbase-0.0.2rc0.dist-info/WHEEL
pytest_elbase-0.0.2rc0.dist-info/top_level.txt
pytest_elbase-0.0.2rc0.dist-info/RECORD
