Metadata-Version: 2.4
Name: pytest-elbase
Version: 0.0.2rc0
Summary: Elbase pytest plugin
Home-page: https://elbase.io
Author: Elbase Packaging
Author-email: pkg@elbase.io
Project-URL: Documentation, https://docs.elbase.io
Classifier: Programming Language :: Python :: 3
Requires-Python: >=3.7, <4
License-File: LICENSE
Dynamic: author
Dynamic: author-email
Dynamic: classifier
Dynamic: description
Dynamic: description-content-type
Dynamic: home-page
Dynamic: license-file
Dynamic: project-url
Dynamic: requires-python
Dynamic: summary
